Metadata-Version: 1.0
Name: hello_world_lizixi
Version: 0.0.3
Summary: a Python module to say hello world
Home-page: UNKNOWN
Author: UNKNOWN
Author-email: UNKNOWN
License: UNKNOWN
Platform: UNKNOWN
